pl_liblab_lotr_sdk/__init__.py
pl_liblab_lotr_sdk/api.py
pl_liblab_lotr_sdk/models.py
pl_liblab_lotr_sdk-0.0.2.dist-info/LICENSE
pl_liblab_lotr_sdk-0.0.2.dist-info/METADATA
pl_liblab_lotr_sdk-0.0.2.dist-info/WHEEL
pl_liblab_lotr_sdk-0.0.2.dist-info/RECORD
